setup.py
fqn/__init__.py
fqn.egg-info/PKG-INFO
fqn.egg-info/SOURCES.txt
fqn.egg-info/dependency_links.txt
fqn.egg-info/top_level.txt