Metadata-Version: 1.0
Name: fqn
Version: 0.7.0
Summary: Functions that can retrieve objects using Fully Qualified Names
Home-page: UNKNOWN
Author: Brian Lauber
Author-email: constructible.truth@gmail.com
License: UNKNOWN
Platform: UNKNOWN
